xtradict/__init__.py
xtradict-0.3.2.dist-info/LICENSE
xtradict-0.3.2.dist-info/METADATA
xtradict-0.3.2.dist-info/WHEEL
xtradict-0.3.2.dist-info/top_level.txt
xtradict-0.3.2.dist-info/RECORD
